microlive/__init__.py
microlive/imports.py
microlive/microscopy.py
microlive/ml_spot_detection.py
microlive/data/__init__.py
microlive/data/icons/__init__.py
microlive/data/icons/icon_micro.png
microlive/data/models/__init__.py
microlive/data/models/spot_detection_cnn.pth
microlive/gui/__init__.py
microlive/gui/app.py
microlive/gui/main.py
microlive/gui/micro_mac.command
microlive/gui/micro_windows.bat
microlive/pipelines/__init__.py
microlive/pipelines/pipeline_FRAP.py
microlive/pipelines/pipeline_folding_efficiency.py
microlive/pipelines/pipeline_particle_tracking.py
microlive/pipelines/pipeline_spot_detection_no_tracking.py
microlive/utils/__init__.py
microlive/utils/device.py
microlive/utils/model_downloader.py
microlive/utils/resources.py
microlive-1.0.14.dist-info/METADATA
microlive-1.0.14.dist-info/WHEEL
microlive-1.0.14.dist-info/entry_points.txt
microlive-1.0.14.dist-info/licenses/LICENSE
microlive-1.0.14.dist-info/RECORD
