Metadata-Version: 2.4
Name: microlive
Version: 1.0.14
Summary: Live-cell microscopy image analysis and single-molecule measurements
Project-URL: Homepage, https://github.com/ningzhaoAnschutz/microlive
Project-URL: Documentation, https://github.com/ningzhaoAnschutz/microlive/blob/main/docs/user_guide.md
Project-URL: Repository, https://github.com/ningzhaoAnschutz/microlive
Project-URL: Issues, https://github.com/ningzhaoAnschutz/microlive/issues
Project-URL: Changelog, https://github.com/ningzhaoAnschutz/microlive/releases
Author: Luis U. Aguilera, William S. Raymond, Rhiannon M. Sears, Nathan L. Nowling, Brian Munsky, Ning Zhao
License-Expression: GPL-3.0-or-later
License-File: LICENSE
Keywords: PyQt5,bioimaging,cellpose,image-analysis,live-cell,microscopy,particle-tracking,single-molecule,tracking
Classifier: Development Status :: 4 - Beta
Classifier: Environment :: X11 Applications :: Qt
Classifier: Intended Audience :: Science/Research
Classifier: License :: OSI Approved :: GNU General Public License v3 (GPLv3)
Classifier: Operating System :: MacOS :: MacOS X
Classifier: Operating System :: Microsoft :: Windows
Classifier: Operating System :: OS Independent
Classifier: Operating System :: POSIX :: Linux
Classifier: Programming Language :: Python :: 3
Classifier: Programming Language :: Python :: 3.10
Classifier: Programming Language :: Python :: 3.11
Classifier: Programming Language :: Python :: 3.12
Classifier: Topic :: Scientific/Engineering :: Bio-Informatics
Classifier: Topic :: Scientific/Engineering :: Image Processing
Classifier: Topic :: Scientific/Engineering :: Visualization
Requires-Python: >=3.10
Requires-Dist: big-fish>=0.6
Requires-Dist: bioio-base==3.1.0
Requires-Dist: bioio-lif>=1.2
Requires-Dist: bioio==3.1.0
Requires-Dist: biopython>=1.81
Requires-Dist: brokenaxes
Requires-Dist: cellpose==3.1.0
Requires-Dist: dask==2024.8.0
Requires-Dist: distributed==2024.8.0
Requires-Dist: dna-features-viewer>=3.1
Requires-Dist: fpdf>=1.7
Requires-Dist: imagecodecs
Requires-Dist: imageio>=2.34
Requires-Dist: ipython
Requires-Dist: ipywidgets
Requires-Dist: joblib>=1.3
Requires-Dist: joypy
Requires-Dist: llvmlite==0.43.0
Requires-Dist: matplotlib-scalebar
Requires-Dist: matplotlib==3.9.2
Requires-Dist: natsort
Requires-Dist: numba==0.60.0
Requires-Dist: numpy==1.26.4
Requires-Dist: opencv-python-headless>=4.9
Requires-Dist: openpyxl>=3.1
Requires-Dist: pandas==2.2.2
Requires-Dist: pillow>=10.0
Requires-Dist: psutil
Requires-Dist: pydantic>=2.0
Requires-Dist: pyqt5>=5.15
Requires-Dist: pystackreg>=0.2.8
Requires-Dist: pyyaml>=6.0
Requires-Dist: readlif==0.6.5
Requires-Dist: roifile
Requires-Dist: scikit-image==0.24.0
Requires-Dist: scikit-learn==1.5.2
Requires-Dist: scipy==1.13.1
Requires-Dist: seaborn==0.13.2
Requires-Dist: snapgene-reader>=0.1
Requires-Dist: statsmodels==0.14.4
Requires-Dist: tifffile>=2024.1
Requires-Dist: tqdm>=4.66
Requires-Dist: trackpy>=0.6
Provides-Extra: dev
Requires-Dist: black>=23.0; extra == 'dev'
Requires-Dist: build; extra == 'dev'
Requires-Dist: isort>=5.12; extra == 'dev'
Requires-Dist: mypy>=1.5; extra == 'dev'
Requires-Dist: pdoc; extra == 'dev'
Requires-Dist: pytest-qt>=4.0; extra == 'dev'
Requires-Dist: pytest>=7.0; extra == 'dev'
Requires-Dist: ruff>=0.1; extra == 'dev'
Requires-Dist: twine; extra == 'dev'
Provides-Extra: notebooks
Requires-Dist: bqplot; extra == 'notebooks'
Requires-Dist: ipympl>=0.9; extra == 'notebooks'
Requires-Dist: ipywidgets>=8.0; extra == 'notebooks'
Requires-Dist: jupyter>=1.0; extra == 'notebooks'
